nats_client/__init__.py
nats_client/apps.py
nats_client/clients.py
nats_client/exceptions.py
nats_client/handlers.py
nats_client/management/commands/nats_listener.py
nats_client/registry.py
nats_client/types.py
nats_client/utils.py
django_nats_client-0.4.3.dist-info/LICENSE
django_nats_client-0.4.3.dist-info/METADATA
django_nats_client-0.4.3.dist-info/WHEEL
django_nats_client-0.4.3.dist-info/RECORD
