Metadata-Version: 2.1
Name: django-nats-client
Version: 0.4.3
Summary: 
Home-page: https://github.com/C0D1UM/django-nats-client
License: MIT
Keywords: django,nats,listener,python
Author: CODIUM
Author-email: support@codium.co
Requires-Python: >=3.8,<4.0
Classifier: License :: OSI Approved :: MIT License
Classifier: Programming Language :: Python :: 3
Classifier: Programming Language :: Python :: 3.8
Classifier: Programming Language :: Python :: 3.9
Classifier: Programming Language :: Python :: 3.10
Classifier: Programming Language :: Python :: 3.11
Requires-Dist: django (>=3.1)
Requires-Dist: jsonpickle (>=3.0,<4.0)
Requires-Dist: nats-py (>=2,<3)
Project-URL: Repository, https://github.com/C0D1UM/django-nats-client
